<?xml version="1.0" encoding="UTF-8"?>
<snippetsTree>
 <snippets file="curculionidae.hostplant/PMC4134251/results/species/genussp/results.xml">
  <result pre=" " exact="Metarhizium spp" xpath="/html[1]/body[1]/div[2]/div[5]/div[2]/p[1]" match="Metarhizium spp" post=". produce a wide array of small molecules including destruxins (DTXs), cyclic depsipeptides which a" name="genussp"/>
  <result pre="a were topically applied to insect larvae. This supports the conclusions of a previous report that " exact="Metarhizium spp" xpath="/html[1]/body[1]/div[2]/div[5]/div[2]/p[1]" match="Metarhizium spp" post=". isolates could be pathogenic for insects whether they had the ability to produce in vitro " name="genussp"/>
  <result pre="Twenty " exact="Metarhizium spp" xpath="/html[1]/body[1]/div[2]/div[5]/div[2]/p[1]" match="Metarhizium spp" post=". isolates were used in the present study: 18 isolates from different regions of Brazil, one from t" name="genussp"/>
  <result pre="Of the 20 " exact="Metarhizium spp" xpath="/html[1]/body[1]/div[2]/div[5]/div[2]/p[1]" match="Metarhizium spp" post=". isolates examined in the current study, one (ARSEF 2575) was previously known to produce high lev" name="genussp"/>
  <result pre="The virulence of 20 " exact="Metarhizium spp" xpath="/html[1]/body[1]/div[2]/div[5]/div[2]/p[1]" match="Metarhizium spp" post=". isolates ( Table 1) was surveyed using two different insect hosts: &lt;" name="genussp"/>
  <result pre="The present study investigated 20 " exact="Metarhizium spp" xpath="/html[1]/body[1]/div[2]/div[5]/div[2]/p[1]" match="Metarhizium spp" post=". isolates as to their virulence against two insect species and their levels of DTXs production in " name="genussp"/>
  <result pre="Comparisons of DTXs production in vitro with virulence to insects of the 20 " exact="Metarhizium spp" xpath="/html[1]/body[1]/div[2]/div[5]/div[2]/p[1]" match="Metarhizium spp" post=". isolates did not indicate a close association of the two traits. The most virulent isolates for &lt;" name="genussp"/>
  <result pre=" " exact="Metarhizium spp" xpath="/html[1]/body[1]/div[2]/div[5]/div[2]/p[1]" match="Metarhizium spp" post=". have been indicated as mediators of interactions among plants, insects and soil: e.g., Behie et a" name="genussp"/>
  <result pre=" Destruxin production (mg/L) by 12 " exact="Metarhizium spp" match="Metarhizium spp" post=". isolates in vitro . Destruxin production is represented by mean values ± standard error" name="genussp"/>
 </snippets>
</snippetsTree>
