{
  "id": [
    "PMC3131009"
  ],
  "source": [
    "PMC"
  ],
  "pmcid": [
    "PMC3131009"
  ],
  "title": [
    "In memoriam: Konjev Desender (1956–2008) and Jean-Pierre Maelfait (1951–2009)."
  ],
  "authorString": [
    "Lövei GL."
  ],
  "authorList": [
    {
      "author": [
        {
          "fullName": [
            "Lövei GL"
          ],
          "firstName": [
            "Gábor L."
          ],
          "lastName": [
            "Lövei"
          ],
          "initials": [
            "GL"
          ],
          "affiliation": [
            "Aarhus University, Faculty of Agricultural Sciences, Department of Integrated Pest Management, Flakkebjerg Research Centre, DK-4200 Slagelse, Denmark"
          ]
        }
      ]
    }
  ],
  "journalInfo": [
    {
      "issue": [
        "100"
      ],
      "journalIssueId": [
        "1846763"
      ],
      "dateOfPublication": [
        "2011 "
      ],
      "monthOfPublication": [
        "0"
      ],
      "yearOfPublication": [
        "2011"
      ],
      "printPublicationDate": [
        "2011-01-01"
      ],
      "journal": [
        {
          "title": [
            "ZooKeys"
          ],
          "ISOAbbreviation": [
            "Zookeys"
          ],
          "medlineAbbreviation": [
            "Zookeys"
          ],
          "NLMid": [
            "101497933"
          ],
          "ISSN": [
            "1313-2989"
          ],
          "ESSN": [
            "1313-2970"
          ]
        }
      ]
    }
  ],
  "pageInfo": [
    "1-36"
  ],
  "affiliation": [
    "Aarhus University, Faculty of Agricultural Sciences, Department of Integrated Pest Management, Flakkebjerg Research Centre, DK-4200 Slagelse, Denmark"
  ],
  "language": [
    "eng"
  ],
  "pubModel": [
    "Undetermined"
  ],
  "pubTypeList": [
    {
      "pubType": [
        "Obituary"
      ]
    }
  ],
  "fullTextUrlList": [
    {
      "fullTextUrl": [
        {
          "availability": [
            "Free"
          ],
          "availabilityCode": [
            "F"
          ],
          "documentStyle": [
            "pdf"
          ],
          "site": [
            "Europe_PMC"
          ],
          "url": [
            "http://europepmc.org/articles/PMC3131009?pdf=render"
          ]
        },
        {
          "availability": [
            "Free"
          ],
          "availabilityCode": [
            "F"
          ],
          "documentStyle": [
            "html"
          ],
          "site": [
            "Europe_PMC"
          ],
          "url": [
            "http://europepmc.org/articles/PMC3131009"
          ]
        },
        {
          "availability": [
            "Free"
          ],
          "availabilityCode": [
            "F"
          ],
          "documentStyle": [
            "pdf"
          ],
          "site": [
            "PubMedCentral"
          ],
          "url": [
            "http://www.pubmedcentral.org/articles/PMC3131009/pdf/?tool=EBI"
          ]
        },
        {
          "availability": [
            "Free"
          ],
          "availabilityCode": [
            "F"
          ],
          "documentStyle": [
            "html"
          ],
          "site": [
            "PubMedCentral"
          ],
          "url": [
            "http://www.pubmedcentral.org/articles/PMC3131009/?tool=EBI"
          ]
        }
      ]
    }
  ],
  "isOpenAccess": [
    "Y"
  ],
  "inEPMC": [
    "Y"
  ],
  "inPMC": [
    "Y"
  ],
  "hasPDF": [
    "Y"
  ],
  "hasBook": [
    "N"
  ],
  "hasSuppl": [
    "N"
  ],
  "citedByCount": [
    "0"
  ],
  "hasReferences": [
    "N"
  ],
  "hasTextMinedTerms": [
    "Y"
  ],
  "hasDbCrossReferences": [
    "N"
  ],
  "hasLabsLinks": [
    "N"
  ],
  "license": [
    "cc by"
  ],
  "epmcAuthMan": [
    "N"
  ],
  "hasTMAccessionNumbers": [
    "N"
  ],
  "dateOfCreation": [
    "2011-08-09"
  ],
  "dateOfRevision": [
    "2014-09-16"
  ],
  "electronicPublicationDate": [
    "2011-05-20"
  ],
  "firstPublicationDate": [
    "2011-05-20"
  ],
  "luceneScore": [
    "NaN"
  ]
}